{
    "muralUrl": "https://www.muralconservancy.org/murals/untitled-57",
    "images": [
        "https://www.muralconservancy.org/sites/default/files/styles/galleryformatter_slide/public/murals/IMG0037_2_8.jpg"
    ],
    "images_total": 1,
    "artist": "Casey Bernay",
    "location": "Ninth Nebula Comic Book Store.\u00a011517 Burbank Blvd., North Hollywood, CA 91601.",
    "location_url": "http://maps.google.com/maps?q=11517+Burbank+Blvd.,+North+Hollywood,+CA&hl=en&sll=34.168922,-118.450904&sspn=0.006649,0.013776&t=h&hnear=11517+Burbank+Blvd,+North+Hollywood,+Los+Angeles,+California+91601&z=17",
    "size": "N/A",
    "medium": "N/A",
    "date": "1989",
    "types": [
        "Contemporary"
    ],
    "description": "Hand signal in style of art found in Dr. Strange comics."
}