{
    "muralUrl": "https://www.muralconservancy.org/murals/pride-mar-vista",
    "images": [
        "https://www.muralconservancy.org/sites/default/files/styles/galleryformatter_slide/public/murals/IMG0029_2_1.jpg",
        "https://www.muralconservancy.org/sites/default/files/styles/galleryformatter_slide/public/murals/IMG0030_2_1.jpg",
        "https://www.muralconservancy.org/sites/default/files/styles/galleryformatter_slide/public/murals/IMG0031_2_2.jpg"
    ],
    "images_total": 3,
    "artist": "East Los Streetscapers",
    "location": "11965 Allin St.,\u00a0Los Angeles, CA 90230.",
    "location_url": "http://maps.google.com/maps?q=11965+Allin+St.,+Mar+vista,+CA&hl=en&sll=34.057604,-118.193905&sspn=0.011857,0.021694&vpsrc=0&hnear=11965+Allin+St,+Los+Angeles,+California+90230&t=h&z=16",
    "size": "30' X 10' ft",
    "medium": "Acrylic",
    "date": "1988",
    "types": [
        "Community"
    ],
    "description": "East Los Streetscapers (Wayne Healy and David Botello), assisted by Daniel Fernandez, Ricardo Lopez, Omar Ross, Bert Juarez, Saul Marquez, Rudy Reyes, Peter Moc, and Ronald Rivera. Reflecting the African American and Mexican American composition of the neighborhood, the mural draws upon ancient African and Mexican traditions as well as imagery of contemporary family life. Sponsored and commissioned by SPARC. Photo: \u00a9 Robin Dunitz"
}