{
    "muralUrl": "https://www.muralconservancy.org/murals/your-travel-agent",
    "images": [
        "https://www.muralconservancy.org/sites/default/files/styles/galleryformatter_slide/public/murals/IMG0004_2_2.jpg"
    ],
    "images_total": 1,
    "artist": "Jane Golden",
    "location": "1842 14th St. Santa Monica, CA. 90404",
    "location_url": "http://maps.google.com/maps?q=1842+14th+St.+Santa+Monica,+CA.&hl=en&ll=34.017594,-118.478065&spn=0.023157,0.045447&sll=34.017546,-118.478054&layer=c&cbp=13,250.03,,0,14.2&cbll=34.017512,-118.477983&gl=us&hnear=1842+14th+St,+Santa+Monica,+California+90404&t=m&z=15&vpsrc=0&panoid=TpFk48N8kvosQGKpn8K30w",
    "size": "20' X 30' ft",
    "medium": "Acrylic",
    "date": "1976",
    "types": [
        "Historic"
    ],
    "description": "Artists: Jane Golden and Peggy Edwards."
}